agora-cli
setup.py
Agora_Client.egg-info/PKG-INFO
Agora_Client.egg-info/SOURCES.txt
Agora_Client.egg-info/dependency_links.txt
Agora_Client.egg-info/namespace_packages.txt
Agora_Client.egg-info/requires.txt
Agora_Client.egg-info/top_level.txt
agora/__init__.py
agora/client/__init__.py
agora/client/execution.py
agora/client/namespaces.py
agora/client/wrapper.py
agora/client/test/__init__.py
agora/client/test/test_parse.py