Metadata-Version: 1.1
Name: Agora-Client
Version: 0.4.18
Summary: An Agora client for Python that requests and executes search plans for graph patterns
Home-page: https://github.com/smartdeveloperhub/agora-client
Author: Fernando Serena
Author-email: fernando.serena@centeropenmiddleware.com
License: Apache 2
Download-URL: https://github.com/smartdeveloperhub/agora-client/tarball/0.4.8-alpha1
Keywords: agora,linked-data,search-plan
Platform: UNKNOWN
